{"description":"should have Codestellar in title|Codestellar website","passed":true,"pending":false,"os":"Windows NT","sessionId":"c60c89b86b0616b98a8133d8366eddbc","browser":{"name":"chrome","version":"63.0.3239.132"},"message":"Passed.","trace":"","browserLogs":[{"level":"WARNING","message":"http://codestellar.net/ - The SSL certificate used to load resources from https://www.payumoney.com will be distrusted in M66. Once distrusted, users will be prevented from loading these resources. See https://g.co/chrome/symantecpkicerts for more information.","timestamp":1519128859762,"type":""},{"level":"SEVERE","message":"http://codestellar.net/ 158:4 Uncaught ReferenceError: odometer is not defined","timestamp":1519128861041,"type":""}],"screenShotFile":"0040007e-00ba-008c-00d9-00cb007b0070.png","timestamp":1519128855487,"duration":6272}
